test/__init__.py
test/test_main.py
test/test_samples.py
yoptions/__init__.py
yoptions/main.py
yoptions-0.0.5.dist-info/licenses/LICENSE.txt
yoptions-0.0.5.dist-info/METADATA
yoptions-0.0.5.dist-info/WHEEL
yoptions-0.0.5.dist-info/top_level.txt
yoptions-0.0.5.dist-info/RECORD
