Metadata-Version: 2.4
Name: yoptions
Version: 0.0.5
Summary: This downloads stock option data and calculates its greeks.
Home-page: https://github.com/Lienus10/yoptions
Author: Julius Langer
Author-email: julius.langer@outlook.de
Classifier: Development Status :: 3 - Alpha
Classifier: Topic :: Office/Business :: Financial :: Investment
Classifier: License :: OSI Approved :: MIT License
Classifier: Programming Language :: Python :: 3
Classifier: Programming Language :: Python :: 3.6
Classifier: Programming Language :: Python :: 3.7
Classifier: Programming Language :: Python :: 3.8
Classifier: Programming Language :: Python :: 3.9
Requires-Python: >=3.6, <4
License-File: LICENSE.txt
Requires-Dist: xmltodict
Dynamic: author
Dynamic: author-email
Dynamic: classifier
Dynamic: description
Dynamic: description-content-type
Dynamic: home-page
Dynamic: license-file
Dynamic: requires-dist
Dynamic: requires-python
Dynamic: summary
